{
  "tarefas": [
    {
      "id": 1,
      "titulo": "Aprender JavaScript",
      "concluido": false
    },
    {
      "id": 2,
      "titulo": "Aprender Vue",
      "concluido": false
    },
    {
      "id": 3,
      "titulo": "Aprender Axios",
      "concluido": false
    },
    {
      "titulo": "Docker",
      "concluido": false,
      "id": 5,
      "curso": "Vue.JS"
    },
    {
      "titulo": "Estudar para SAA-C03",
      "concluido": false,
      "id": 6
    },
    {
      "titulo": "AWS Cloud Pratictioner ",
      "id": 7,
      "concluido": false
    }
  ]
}